{
  "uf": "MS",
  "state": "Mato Grosso do Sul",
  "city": "Corumbá",
  "serviceCount": 4,
  "officialServiceCount": 4,
  "services": [
    {
      "id": "ms-curated-corumba-casa-trabalhador",
      "name": "Casa do Trabalhador de Corumbá",
      "category": "trabalho",
      "region": "Centro-Oeste",
      "uf": "MS",
      "state": "Mato Grosso do Sul",
      "city": "Corumbá",
      "address": "Rua 15 de Novembro, nº 32, primeiro andar, Centro",
      "map": "https://www.google.com/maps/search/?api=1&query=Rua%2015%20de%20Novembro%2C%20n%C2%BA%2032%2C%20primeiro%20andar%2C%20Centro%2C%20Corumb%C3%A1%20-%20MS",
      "phone": "",
      "phoneLabel": "Não informado na fonte oficial",
      "hours": "Segunda a sexta, das 7h30 às 12h30",
      "source": "Fundação do Trabalho de Mato Grosso do Sul",
      "sourceUrl": "https://www.funtrab.ms.gov.br/funtrab-no-interior-semana-26-08-2024-a-30-08-2024/",
      "verified": "02/07/2026",
      "contactConfirmed": false,
      "addressSpecific": true,
      "hoursInformed": true,
      "sourceRegistered": true,
      "priority": "Alta",
      "reasons": [
        "Telefone direto não informado na fonte"
      ],
      "notice": "Fonte oficial consultada em 02/07/2026. Confirme antes de se deslocar."
    },
    {
      "id": "ms-curated-corumba-cras-i",
      "name": "CRAS I — Centro América",
      "category": "assistencia",
      "region": "Centro-Oeste",
      "uf": "MS",
      "state": "Mato Grosso do Sul",
      "city": "Corumbá",
      "address": "Rua Cáceres, s/n, Centro América",
      "map": "https://www.google.com/maps/search/?api=1&query=Rua%20C%C3%A1ceres%2C%20s%2Fn%2C%20Centro%20Am%C3%A9rica%2C%20Corumb%C3%A1%20-%20MS",
      "phone": "(67) 98191-0115",
      "phoneLabel": "(67) 98191-0115",
      "hours": "Segunda a sexta, das 7h30 às 13h30",
      "source": "Prefeitura Municipal de Corumbá",
      "sourceUrl": "https://corumba.ms.gov.br/locais/11",
      "verified": "02/07/2026",
      "contactConfirmed": true,
      "addressSpecific": true,
      "hoursInformed": true,
      "sourceRegistered": true,
      "priority": "Baixa",
      "reasons": [],
      "notice": "Fonte oficial consultada em 02/07/2026. Confirme antes de se deslocar."
    },
    {
      "id": "ms-curated-corumba-procon",
      "name": "Procon Municipal de Corumbá",
      "category": "outros",
      "region": "Centro-Oeste",
      "uf": "MS",
      "state": "Mato Grosso do Sul",
      "city": "Corumbá",
      "address": "Avenida General Rondon, nº 1206, Centro",
      "map": "https://www.google.com/maps/search/?api=1&query=Avenida%20General%20Rondon%2C%20n%C2%BA%201206%2C%20Centro%2C%20Corumb%C3%A1%20-%20MS",
      "phone": "(67) 98191-0203",
      "phoneLabel": "(67) 98191-0203",
      "hours": "Segunda a sexta, das 7h30 às 13h30",
      "source": "Prefeitura Municipal de Corumbá",
      "sourceUrl": "https://corumba.ms.gov.br/noticias/procon-intensifica-monitoramento-de-precos-de-combustiveis-e-reforca-fiscalizacao",
      "verified": "02/07/2026",
      "contactConfirmed": true,
      "addressSpecific": true,
      "hoursInformed": true,
      "sourceRegistered": true,
      "priority": "Baixa",
      "reasons": [],
      "notice": "Fonte oficial consultada em 02/07/2026. Confirme antes de se deslocar."
    },
    {
      "id": "ms-curated-corumba-pronto-socorro",
      "name": "Pronto-Socorro Municipal de Corumbá",
      "category": "saude",
      "region": "Centro-Oeste",
      "uf": "MS",
      "state": "Mato Grosso do Sul",
      "city": "Corumbá",
      "address": "Rua Colombo, s/n, entre as ruas 15 de Novembro e 7 de Setembro, Centro",
      "map": "https://www.google.com/maps/search/?api=1&query=Rua%20Colombo%2C%20s%2Fn%2C%20entre%20as%20ruas%2015%20de%20Novembro%20e%207%20de%20Setembro%2C%20Centro%2C%20Corumb%C3%A1%20-%20MS",
      "phone": "(67) 3231-5642 / (67) 3907-5380",
      "phoneLabel": "(67) 3231-5642 / (67) 3907-5380",
      "hours": "24h por dia",
      "source": "Diário Oficial do Município de Corumbá",
      "sourceUrl": "https://do.corumba.ms.gov.br/legislacao/corumba/detalhes/44388",
      "verified": "02/07/2026",
      "contactConfirmed": true,
      "addressSpecific": true,
      "hoursInformed": true,
      "sourceRegistered": true,
      "priority": "Baixa",
      "reasons": [],
      "notice": "Fonte oficial consultada em 02/07/2026. Confirme antes de se deslocar."
    }
  ]
}
